sparkhistogram/__init__.py
sparkhistogram/histogram.py
sparkhistogram-0.4.dist-info/METADATA
sparkhistogram-0.4.dist-info/WHEEL
sparkhistogram-0.4.dist-info/top_level.txt
sparkhistogram-0.4.dist-info/RECORD
