Metadata-Version: 2.1
Name: sparkhistogram
Version: 0.4
Summary: Sparkhistogram contains helper functions for generating data histograms with the Spark DataFrame API.
Home-page: https://github.com/LucaCanali/Miscellaneous/blob/master/Spark_Notes/Spark_DataFrame_Histograms.md
Author: Luca Canali
Author-email: luca.canali@cern.ch
License: Apache License, Version 2.0
Classifier: Programming Language :: Python :: 3
Classifier: Operating System :: OS Independent
Classifier: License :: OSI Approved :: Apache Software License
Classifier: Intended Audience :: Developers
Classifier: Development Status :: 4 - Beta
Requires-Python: >=3.6
